jupyter_vis3d/__init__.py
jupyter_vis3d/_version.py
jupyter_vis3d/example.py
jupyter_vis3d/labextension/package.json
jupyter_vis3d/labextension/static/261.470235cd97287e0262d5.js
jupyter_vis3d/labextension/static/261.c64b134e8dcb1e23838b.js
jupyter_vis3d/labextension/static/486.0165ebb930b2c1611f04.js
jupyter_vis3d/labextension/static/486.0165ebb930b2c1611f04.js.LICENSE.txt
jupyter_vis3d/labextension/static/568.595214e475846444ad3d.js
jupyter_vis3d/labextension/static/568.828198c7b5392c313eab.js
jupyter_vis3d/labextension/static/825.3d29eb5a4a78a8d579f3.js
jupyter_vis3d/labextension/static/remoteEntry.1020371875928215c593.js
jupyter_vis3d/labextension/static/remoteEntry.f9799ec9c913b39dd82c.js
jupyter_vis3d/labextension/static/remoteEntry.f9ce352f8e977ca99c8a.js
jupyter_vis3d/labextension/static/style.js
jupyter_vis3d/nbextension/extension.js
jupyter_vis3d/nbextension/index.js
jupyter_vis3d/nbextension/index.js.LICENSE.txt
jupyter_vis3d-0.1.1a0.data/data/etc/jupyter/nbconfig/notebook.d/jupyter-vis3d.json
jupyter_vis3d-0.1.1a0.data/data/share/jupyter/labextensions/jupyter-vis3d/install.json
jupyter_vis3d-0.1.1a0.data/data/share/jupyter/labextensions/jupyter-vis3d/package.json
jupyter_vis3d-0.1.1a0.data/data/share/jupyter/labextensions/jupyter-vis3d/static/261.470235cd97287e0262d5.js
jupyter_vis3d-0.1.1a0.data/data/share/jupyter/labextensions/jupyter-vis3d/static/486.0165ebb930b2c1611f04.js
jupyter_vis3d-0.1.1a0.data/data/share/jupyter/labextensions/jupyter-vis3d/static/486.0165ebb930b2c1611f04.js.LICENSE.txt
jupyter_vis3d-0.1.1a0.data/data/share/jupyter/labextensions/jupyter-vis3d/static/568.828198c7b5392c313eab.js
jupyter_vis3d-0.1.1a0.data/data/share/jupyter/labextensions/jupyter-vis3d/static/825.3d29eb5a4a78a8d579f3.js
jupyter_vis3d-0.1.1a0.data/data/share/jupyter/labextensions/jupyter-vis3d/static/remoteEntry.f9799ec9c913b39dd82c.js
jupyter_vis3d-0.1.1a0.data/data/share/jupyter/labextensions/jupyter-vis3d/static/style.js
jupyter_vis3d-0.1.1a0.dist-info/LICENSE.txt
jupyter_vis3d-0.1.1a0.dist-info/METADATA
jupyter_vis3d-0.1.1a0.dist-info/WHEEL
jupyter_vis3d-0.1.1a0.dist-info/top_level.txt
jupyter_vis3d-0.1.1a0.dist-info/RECORD
