Metadata-Version: 2.1
Name: jupyter-vis3d
Version: 0.1.1a0
Summary: A custom 3d visualization library
Home-page: https://github.com//jupyter-vis3d
Author: Alex Chen
Author-email: fizban007@gmail.com
License: UNKNOWN
Keywords: ipython,jupyter,widgets
Platform: UNKNOWN
Classifier: Development Status :: 4 - Beta
Classifier: Framework :: IPython
Classifier: Intended Audience :: Developers
Classifier: Intended Audience :: Science/Research
Classifier: Topic :: Multimedia :: Graphics
Classifier: Programming Language :: Python :: 3.6
Classifier: Programming Language :: Python :: 3.7
Classifier: Programming Language :: Python :: 3.8
Classifier: Programming Language :: Python :: 3.9
Requires-Dist: ipywidgets (>=7.6.0)
Requires-Dist: numpy
